utok.py
pyutok-1.2.1.dist-info/LICENSE
pyutok-1.2.1.dist-info/METADATA
pyutok-1.2.1.dist-info/WHEEL
pyutok-1.2.1.dist-info/entry_points.txt
pyutok-1.2.1.dist-info/RECORD
