Metadata-Version: 2.1
Name: pyutok
Version: 1.2.1
Summary: Inspired by a tool I can not find anymore on the internet: utok 1.5. I use it to clean up path settings in large shell script configuration setups.
Home-page: https://python.xn--hllmanns-n4a.de/utok/
License: MIT
Author: Berthold Höllmann
Author-email: berhoel@gmail.com
Requires-Python: >=3.8,<4.0
Classifier: Development Status :: 5 - Production/Stable
Classifier: Environment :: Console
Classifier: Intended Audience :: End Users/Desktop
Classifier: Intended Audience :: System Administrators
Classifier: License :: OSI Approved :: MIT License
Classifier: Operating System :: POSIX
Classifier: Programming Language :: Python :: 3
Classifier: Programming Language :: Python :: 3.8
Classifier: Programming Language :: Python :: 3.9
Classifier: Programming Language :: Python :: 3.10
Classifier: Programming Language :: Python :: 3.11
Classifier: Programming Language :: Python :: 3.12
Classifier: Topic :: System :: Shells
Classifier: Topic :: Utilities
Requires-Dist: setuptools
Project-URL: Documentation, https://python.xn--hllmanns-n4a.de/utok/
Project-URL: Repository, https://gitlab.com/berhoel/python/pyutok.git
